ok_palette_lab/__init__.py
ok_palette_lab/matplotlib.py
ok_palette_lab/plotly.py
ok_palette_lab/py.typed
ok_palette_lab-0.2.0.dist-info/METADATA
ok_palette_lab-0.2.0.dist-info/WHEEL
ok_palette_lab-0.2.0.dist-info/licenses/LICENSE.txt
ok_palette_lab-0.2.0.dist-info/RECORD
