Metadata-Version: 2.4
Name: ok_palette_lab
Version: 0.2.0
Summary: Smooth color maps using Oklch color space for Plotly and matplotlib.
License-Expression: MIT
License-File: LICENSE.txt
Keywords: color map,Oklch
Author: Kenta Kabashima
Author-email: kenta_program37@hotmail.co.jp
Requires-Python: >=3.12,<3.15,!=3.14.1
Classifier: Development Status :: 3 - Alpha
Classifier: Intended Audience :: Developers
Classifier: Intended Audience :: Science/Research
Classifier: License :: OSI Approved :: MIT License
Classifier: Programming Language :: Python :: 3.12
Classifier: Programming Language :: Python :: 3.13
Classifier: Programming Language :: Python :: 3.14
Classifier: Topic :: Scientific/Engineering :: Visualization
Classifier: Typing :: Typed
Provides-Extra: matplotlib
Provides-Extra: plotly
Requires-Dist: matplotlib (>=3) ; extra == "matplotlib"
Requires-Dist: plotly (>=6) ; extra == "plotly"
Project-URL: Documentation, https://okpalettelab.musicscience37.com
Project-URL: Repository, https://gitlab.com/MusicScience37Projects/utility-libraries/OKPaletteLab
